{
  "format": "old_317",
  "vertexCount": 13,
  "triangleCount": 9,
  "textureTriangleCount": 0,
  "verticesX": [-48,-50,-64,-64,-52,-64,-54,-64,-59,-64,-64,-48,-48],
  "verticesY": [-137,-139,-139,-137,-139,-139,-136,-136,-136,-136,-136,-137,-137],
  "verticesZ": [64,64,50,48,64,52,64,54,64,59,64,64,64],
  "triangleA": [0,0,1,1,4,4,6,6,8],
  "triangleB": [1,2,4,5,6,7,8,9,10],
  "triangleC": [2,3,5,2,7,5,9,7,9],
  "triangleColors": [7582,7582,7582,7582,7582,7582,8398,8398,7582],
  "trianglePriorities": [3,3,3,3,3,3,1,1,3]
}
