{
  "format": "old_317",
  "vertexCount": 19,
  "triangleCount": 10,
  "textureTriangleCount": 4,
  "verticesX": [-64,-64,-32,-32,-32,-48,-48,-64,-32,-64,-64,64,64,-32,-32,-160,-160,-64,-64],
  "verticesY": [-240,-240,-240,-240,0,0,-240,0,0,-240,0,0,-240,-240,0,0,-240,-240,-240],
  "verticesZ": [64,32,32,64,64,64,64,32,32,48,48,32,32,160,160,64,64,-80,64],
  "triangleA": [0,0,3,3,3,1,1,2,9,9],
  "triangleB": [1,2,2,4,5,7,8,8,10,7],
  "triangleC": [2,3,4,5,6,8,2,4,7,1],
  "triangleColors": [28,28,2,2,2,2,2,2,2,2],
  "triangleInfo": [0,0,6,10,10,2,2,6,14,14],
  "globalPriority": 1,
  "textureTriangleA": [11,13,15,9],
  "textureTriangleB": [12,14,16,10],
  "textureTriangleC": [7,2,4,17]
}
