{
  "skinList": {
    "boneCount": 10,
    "transformTypes": [0,2,3,5,0,2,5,3,0,1],
    "childIndices": [[0],[0],[0],[0],[1],[1],[1],[1],[0,1],[0,1]]
  },
  "frameCount": 16,
  "frames": [
    {"frameId":0,"transformCount":9,"transforms":[{"bone":2,"x":0,"y":0,"z":0},{"bone":7,"x":0,"y":0,"z":0},{"bone":8,"x":-7,"y":0,"z":0}]},
    {"frameId":1,"transformCount":9,"transforms":[{"bone":2,"x":108,"y":108,"z":108},{"bone":5,"x":0,"y":80,"z":0},{"bone":6,"x":0,"y":1,"z":0},{"bone":7,"x":108,"y":108,"z":108},{"bone":8,"x":-7,"y":0,"z":0}]},
    {"frameId":2,"transformCount":9,"transforms":[{"bone":5,"x":0,"y":-119,"z":0},{"bone":6,"x":0,"y":2,"z":0},{"bone":8,"x":-7,"y":0,"z":0}]},
    {"frameId":3,"transformCount":10,"transforms":[{"bone":5,"x":0,"y":-99,"z":0},{"bone":6,"x":0,"y":1,"z":0},{"bone":8,"x":-7,"y":0,"z":0},{"bone":9,"x":0,"y":-5,"z":0}]},
    {"frameId":4,"transformCount":10,"transforms":[{"bone":5,"x":0,"y":-79,"z":0},{"bone":8,"x":-7,"y":0,"z":0},{"bone":9,"x":0,"y":-8,"z":0}]},
    {"frameId":5,"transformCount":10,"transforms":[{"bone":5,"x":0,"y":-39,"z":0},{"bone":6,"x":0,"y":1,"z":0},{"bone":8,"x":-7,"y":0,"z":0},{"bone":9,"x":0,"y":-5,"z":0}]},
    {"frameId":6,"transformCount":10,"transforms":[{"bone":5,"x":0,"y":-19,"z":0},{"bone":6,"x":0,"y":2,"z":0},{"bone":8,"x":-7,"y":0,"z":0},{"bone":9,"x":0,"y":-2,"z":0}]},
    {"frameId":7,"transformCount":9,"transforms":[{"bone":6,"x":0,"y":1,"z":0},{"bone":8,"x":-7,"y":0,"z":0}]},
    {"frameId":8,"transformCount":9,"transforms":[{"bone":2,"x":0,"y":0,"z":0},{"bone":7,"x":0,"y":0,"z":0},{"bone":8,"x":-7,"y":0,"z":0}]},
    {"frameId":9,"transformCount":9,"transforms":[{"bone":2,"x":0,"y":0,"z":0},{"bone":7,"x":0,"y":0,"z":0},{"bone":8,"x":-7,"y":0,"z":0}]},
    {"frameId":10,"transformCount":9,"transforms":[{"bone":2,"x":0,"y":0,"z":0},{"bone":7,"x":0,"y":0,"z":0},{"bone":8,"x":-7,"y":0,"z":0}]},
    {"frameId":11,"transformCount":9,"transforms":[{"bone":2,"x":8,"y":8,"z":8},{"bone":7,"x":0,"y":0,"z":0},{"bone":8,"x":-7,"y":0,"z":0}]},
    {"frameId":12,"transformCount":9,"transforms":[{"bone":2,"x":28,"y":28,"z":28},{"bone":7,"x":0,"y":0,"z":0},{"bone":8,"x":-7,"y":0,"z":0}]},
    {"frameId":13,"transformCount":9,"transforms":[{"bone":2,"x":48,"y":48,"z":48},{"bone":7,"x":0,"y":0,"z":0},{"bone":8,"x":-7,"y":0,"z":0}]},
    {"frameId":14,"transformCount":9,"transforms":[{"bone":2,"x":68,"y":68,"z":68},{"bone":7,"x":48,"y":48,"z":48},{"bone":8,"x":-7,"y":0,"z":0}]},
    {"frameId":15,"transformCount":9,"transforms":[{"bone":2,"x":88,"y":88,"z":88},{"bone":5,"x":0,"y":40,"z":0},{"bone":7,"x":88,"y":88,"z":88},{"bone":8,"x":-7,"y":0,"z":0}]}
  ]
}
