{
  "skinList": {
    "boneCount": 59,
    "transformTypes": [0,1,2,0,2,0,2,0,2,0,2,0,2,0,2,0,2,0,2,0,2,0,2,0,2,0,2,0,2,0,2,0,2,0,2,0,2,0,2,0,2,0,2,0,2,0,2,0,2,0,2,0,2,0,2,0,1,0,2],
    "childIndices": [[0],[1,2,3,4,5,6,7,8,9,10,11,12,13,14,15,16,17,18,19,20,21,22,23,24,25,26,27,28,29,30,31,32,33,34,35,36,37,38,39,40,41,42,43,44,45,46,47,48,49,0,50,51,52],[1,2,3,4,5,6,7,8,9,10,11,12,13,14,15,16,17,18,19,20,21,22,23,24,25,26,27,28,29,30,31,32,33,34,35,36,37,38,39,40,41,42,43,44,45,46,47,48,49,0,50,51,52],[47],[46,47,48,49],[45],[48,49],[20,21],[16,17,18,19],[18],[16,17,19],[17],[19],[8,20],[12,13,14,15],[15],[12,13,14],[13],[12],[6,8],[7,9,10,11],[7],[9,10,11],[10],[11],[5,6],[1,2,3,4],[3],[1,2,4],[2],[4],[42,47],[38,39,40,41,44],[40],[38,39,41],[38],[41],[27,42],[34,35,36,37],[37],[34,35,36],[35],[34],[30,42],[28,29,31,32,33],[29],[31,32,33],[31],[33],[26,28],[22,23,24,25,26],[24],[22,23,25],[22],[25],[0],[5,6,8,20,21,26,27,30,42,43,44,45,46,47,48,49,0],[53],[1,2,3,4,5,6,7,8,9,10,11,12,13,14,15,16,17,18,19,20,21,22,23,24,25,26,27,28,29,30,31,32,33,34,35,36,37,38,39,40,41,42,43,44,45,46,47,48,49,0]]
  },
  "frameCount": 33,
  "frames": [
    {"frameId":0,"transformCount":57,"transforms":[{"bone":1,"x":0,"y":23,"z":0},{"bone":8,"x":0,"y":8,"z":25},{"bone":10,"x":0,"y":0,"z":-64},{"bone":12,"x":0,"y":0,"z":-27},{"bone":14,"x":0,"y":3,"z":25},{"bone":16,"x":0,"y":0,"z":-64},{"bone":18,"x":0,"y":0,"z":-29},{"bone":20,"x":0,"y":-2,"z":25},{"bone":22,"x":0,"y":0,"z":-64},{"bone":24,"x":0,"y":0,"z":-29},{"bone":26,"x":0,"y":-7,"z":25},{"bone":28,"x":0,"y":0,"z":-64},{"bone":30,"x":0,"y":0,"z":-29},{"bone":32,"x":0,"y":-7,"z":-24},{"bone":34,"x":0,"y":0,"z":65},{"bone":36,"x":0,"y":0,"z":28},{"bone":38,"x":0,"y":-2,"z":-24},{"bone":40,"x":0,"y":0,"z":65},{"bone":42,"x":0,"y":0,"z":30},{"bone":44,"x":0,"y":3,"z":-24},{"bone":46,"x":0,"y":0,"z":65},{"bone":48,"x":0,"y":0,"z":30},{"bone":50,"x":0,"y":6,"z":-24},{"bone":52,"x":0,"y":0,"z":65},{"bone":54,"x":0,"y":0,"z":30},{"bone":56,"x":0,"y":-3,"z":0}]},
    {"frameId":1,"transformCount":59,"transforms":[{"bone":1,"x":0,"y":23,"z":-7},{"bone":6,"x":-4,"y":0,"z":0},{"bone":8,"x":0,"y":3,"z":25},{"bone":10,"x":0,"y":0,"z":-64},{"bone":12,"x":-4,"y":0,"z":-27},{"bone":14,"x":0,"y":0,"z":24},{"bone":16,"x":0,"y":0,"z":-64},{"bone":18,"x":-2,"y":0,"z":-29},{"bone":20,"x":0,"y":-5,"z":21},{"bone":22,"x":0,"y":0,"z":-64},{"bone":24,"x":-3,"y":0,"z":-29},{"bone":26,"x":0,"y":-10,"z":21},{"bone":28,"x":0,"y":0,"z":-64},{"bone":30,"x":-4,"y":0,"z":-29},{"bone":32,"x":0,"y":-2,"z":-24},{"bone":34,"x":0,"y":0,"z":65},{"bone":36,"x":0,"y":0,"z":28},{"bone":38,"x":0,"y":1,"z":-23},{"bone":40,"x":0,"y":0,"z":65},{"bone":42,"x":0,"y":0,"z":30},{"bone":44,"x":0,"y":6,"z":-22},{"bone":46,"x":0,"y":0,"z":65},{"bone":48,"x":0,"y":0,"z":30},{"bone":50,"x":0,"y":8,"z":-20},{"bone":52,"x":0,"y":0,"z":65},{"bone":54,"x":0,"y":0,"z":30},{"bone":56,"x":0,"y":-3,"z":0},{"bone":58,"x":2,"y":0,"z":0}]},
    {"frameId":2,"transformCount":59,"transforms":[{"bone":1,"x":0,"y":23,"z":-15},{"bone":4,"x":0,"y":0,"z":0},{"bone":6,"x":-9,"y":0,"z":0},{"bone":8,"x":0,"y":0,"z":25},{"bone":10,"x":0,"y":0,"z":-64},{"bone":12,"x":-9,"y":0,"z":-27},{"bone":14,"x":0,"y":-4,"z":23},{"bone":16,"x":0,"y":0,"z":-64},{"bone":18,"x":-6,"y":0,"z":-29},{"bone":20,"x":0,"y":-9,"z":18},{"bone":22,"x":0,"y":0,"z":-64},{"bone":24,"x":-8,"y":0,"z":-29},{"bone":26,"x":0,"y":-13,"z":17},{"bone":28,"x":0,"y":0,"z":-64},{"bone":30,"x":-10,"y":0,"z":-29},{"bone":32,"x":0,"y":1,"z":-24},{"bone":34,"x":0,"y":0,"z":65},{"bone":36,"x":0,"y":0,"z":28},{"bone":38,"x":0,"y":5,"z":-22},{"bone":40,"x":0,"y":0,"z":65},{"bone":42,"x":0,"y":0,"z":30},{"bone":44,"x":0,"y":9,"z":-20},{"bone":46,"x":0,"y":0,"z":65},{"bone":48,"x":0,"y":0,"z":30},{"bone":50,"x":0,"y":10,"z":-16},{"bone":52,"x":0,"y":0,"z":65},{"bone":54,"x":0,"y":0,"z":30},{"bone":56,"x":0,"y":-3,"z":0},{"bone":58,"x":5,"y":0,"z":0}]},
    {"frameId":3,"transformCount":59,"transforms":[{"bone":1,"x":0,"y":23,"z":-23},{"bone":4,"x":0,"y":0,"z":0},{"bone":6,"x":-14,"y":0,"z":0},{"bone":8,"x":0,"y":-4,"z":25},{"bone":10,"x":0,"y":0,"z":-64},{"bone":12,"x":-14,"y":0,"z":-27},{"bone":14,"x":0,"y":-8,"z":22},{"bone":16,"x":0,"y":0,"z":-64},{"bone":18,"x":-10,"y":0,"z":-29},{"bone":20,"x":0,"y":-13,"z":15},{"bone":22,"x":0,"y":0,"z":-64},{"bone":24,"x":-12,"y":0,"z":-29},{"bone":26,"x":0,"y":-16,"z":13},{"bone":28,"x":0,"y":0,"z":-64},{"bone":30,"x":-16,"y":0,"z":-29},{"bone":32,"x":0,"y":6,"z":-24},{"bone":34,"x":0,"y":0,"z":65},{"bone":36,"x":0,"y":0,"z":28},{"bone":38,"x":0,"y":9,"z":-21},{"bone":40,"x":0,"y":0,"z":65},{"bone":42,"x":0,"y":0,"z":30},{"bone":44,"x":0,"y":12,"z":-18},{"bone":46,"x":0,"y":0,"z":65},{"bone":48,"x":0,"y":0,"z":30},{"bone":50,"x":0,"y":12,"z":-12},{"bone":52,"x":0,"y":0,"z":65},{"bone":54,"x":0,"y":0,"z":30},{"bone":56,"x":0,"y":-3,"z":0},{"bone":58,"x":7,"y":0,"z":0}]},
    {"frameId":4,"transformCount":59,"transforms":[{"bone":1,"x":0,"y":23,"z":-31},{"bone":4,"x":-1,"y":0,"z":0},{"bone":6,"x":-20,"y":1,"z":0},{"bone":8,"x":0,"y":-9,"z":25},{"bone":10,"x":0,"y":0,"z":-64},{"bone":12,"x":-19,"y":0,"z":-27},{"bone":14,"x":0,"y":-13,"z":21},{"bone":16,"x":0,"y":0,"z":-64},{"bone":18,"x":-14,"y":0,"z":-29},{"bone":20,"x":0,"y":-17,"z":12},{"bone":22,"x":0,"y":0,"z":-64},{"bone":24,"x":-17,"y":0,"z":-29},{"bone":26,"x":0,"y":-20,"z":9},{"bone":28,"x":0,"y":0,"z":-64},{"bone":30,"x":-22,"y":0,"z":-29},{"bone":32,"x":0,"y":11,"z":-24},{"bone":34,"x":0,"y":0,"z":65},{"bone":36,"x":0,"y":0,"z":28},{"bone":38,"x":0,"y":14,"z":-21},{"bone":40,"x":0,"y":0,"z":65},{"bone":42,"x":0,"y":0,"z":30},{"bone":44,"x":0,"y":15,"z":-16},{"bone":46,"x":0,"y":0,"z":65},{"bone":48,"x":0,"y":0,"z":30},{"bone":50,"x":0,"y":14,"z":-8},{"bone":52,"x":0,"y":0,"z":65},{"bone":54,"x":0,"y":0,"z":30},{"bone":56,"x":0,"y":-3,"z":0},{"bone":58,"x":10,"y":0,"z":0}]},
    {"frameId":5,"transformCount":57,"transforms":[{"bone":1,"x":0,"y":23,"z":0},{"bone":8,"x":0,"y":8,"z":25},{"bone":10,"x":0,"y":0,"z":-64},{"bone":12,"x":0,"y":0,"z":-27},{"bone":14,"x":0,"y":3,"z":25},{"bone":16,"x":0,"y":0,"z":-64},{"bone":18,"x":0,"y":0,"z":-29},{"bone":20,"x":0,"y":-2,"z":25},{"bone":22,"x":0,"y":0,"z":-64},{"bone":24,"x":0,"y":0,"z":-29},{"bone":26,"x":0,"y":-7,"z":25},{"bone":28,"x":0,"y":0,"z":-64},{"bone":30,"x":0,"y":0,"z":-29},{"bone":32,"x":0,"y":-7,"z":-24},{"bone":34,"x":0,"y":0,"z":65},{"bone":36,"x":0,"y":0,"z":28},{"bone":38,"x":0,"y":-2,"z":-24},{"bone":40,"x":0,"y":0,"z":65},{"bone":42,"x":0,"y":0,"z":30},{"bone":44,"x":0,"y":3,"z":-24},{"bone":46,"x":0,"y":0,"z":65},{"bone":48,"x":0,"y":0,"z":30},{"bone":50,"x":0,"y":6,"z":-24},{"bone":52,"x":0,"y":0,"z":65},{"bone":54,"x":0,"y":0,"z":30},{"bone":56,"x":0,"y":-3,"z":0}]},
    {"frameId":6,"transformCount":59,"transforms":[{"bone":1,"x":0,"y":40,"z":0},{"bone":4,"x":-2,"y":-12,"z":-6},{"bone":6,"x":90,"y":5,"z":0},{"bone":8,"x":0,"y":20,"z":9},{"bone":10,"x":0,"y":0,"z":-29},{"bone":12,"x":0,"y":0,"z":1},{"bone":14,"x":0,"y":3,"z":21},{"bone":16,"x":0,"y":0,"z":-46},{"bone":18,"x":0,"y":0,"z":-29},{"bone":20,"x":0,"y":-2,"z":13},{"bone":22,"x":0,"y":0,"z":-26},{"bone":24,"x":0,"y":0,"z":-29},{"bone":26,"x":0,"y":-15,"z":24},{"bone":28,"x":0,"y":0,"z":-39},{"bone":30,"x":0,"y":0,"z":-29},{"bone":32,"x":0,"y":-14,"z":-5},{"bone":34,"x":0,"y":0,"z":23},{"bone":36,"x":0,"y":0,"z":28},{"bone":38,"x":0,"y":-2,"z":-6},{"bone":40,"x":0,"y":0,"z":22},{"bone":42,"x":0,"y":0,"z":30},{"bone":44,"x":0,"y":3,"z":-7},{"bone":46,"x":0,"y":0,"z":24},{"bone":48,"x":0,"y":0,"z":30},{"bone":50,"x":0,"y":12,"z":-13},{"bone":52,"x":0,"y":0,"z":29},{"bone":54,"x":0,"y":0,"z":30},{"bone":56,"x":0,"y":9,"z":0},{"bone":58,"x":-3,"y":0,"z":0}]},
    {"frameId":7,"transformCount":59,"transforms":[{"bone":1,"x":0,"y":23,"z":0},{"bone":4,"x":-5,"y":-8,"z":-4},{"bone":6,"x":2,"y":-5,"z":0},{"bone":8,"x":0,"y":8,"z":22},{"bone":10,"x":0,"y":0,"z":-64},{"bone":12,"x":0,"y":0,"z":-27},{"bone":14,"x":0,"y":3,"z":24},{"bone":16,"x":0,"y":0,"z":-64},{"bone":18,"x":0,"y":0,"z":-29},{"bone":20,"x":0,"y":-2,"z":25},{"bone":22,"x":0,"y":0,"z":-64},{"bone":24,"x":0,"y":0,"z":-29},{"bone":26,"x":0,"y":-7,"z":27},{"bone":28,"x":0,"y":0,"z":-64},{"bone":30,"x":0,"y":0,"z":-29},{"bone":32,"x":0,"y":-7,"z":-21},{"bone":34,"x":0,"y":0,"z":65},{"bone":36,"x":0,"y":0,"z":28},{"bone":38,"x":0,"y":-2,"z":-23},{"bone":40,"x":0,"y":0,"z":65},{"bone":42,"x":0,"y":0,"z":30},{"bone":44,"x":0,"y":3,"z":-24},{"bone":46,"x":0,"y":0,"z":65},{"bone":48,"x":0,"y":0,"z":30},{"bone":50,"x":0,"y":6,"z":-26},{"bone":52,"x":0,"y":0,"z":65},{"bone":54,"x":0,"y":0,"z":30},{"bone":56,"x":0,"y":-3,"z":0},{"bone":58,"x":-3,"y":0,"z":0}]},
    {"frameId":8,"transformCount":59,"transforms":[{"bone":1,"x":0,"y":23,"z":0},{"bone":4,"x":-11,"y":-17,"z":-10},{"bone":6,"x":5,"y":-11,"z":0},{"bone":8,"x":0,"y":8,"z":20},{"bone":10,"x":0,"y":0,"z":-64},{"bone":12,"x":0,"y":0,"z":-27},{"bone":14,"x":0,"y":3,"z":24},{"bone":16,"x":0,"y":0,"z":-64},{"bone":18,"x":0,"y":0,"z":-29},{"bone":20,"x":0,"y":-2,"z":25},{"bone":22,"x":0,"y":0,"z":-64},{"bone":24,"x":0,"y":0,"z":-29},{"bone":26,"x":0,"y":-7,"z":30},{"bone":28,"x":0,"y":0,"z":-64},{"bone":30,"x":0,"y":0,"z":-29},{"bone":32,"x":0,"y":-7,"z":-19},{"bone":34,"x":0,"y":0,"z":65},{"bone":36,"x":0,"y":0,"z":28},{"bone":38,"x":0,"y":-2,"z":-23},{"bone":40,"x":0,"y":0,"z":65},{"bone":42,"x":0,"y":0,"z":30},{"bone":44,"x":0,"y":3,"z":-24},{"bone":46,"x":0,"y":0,"z":65},{"bone":48,"x":0,"y":0,"z":30},{"bone":50,"x":0,"y":6,"z":-29},{"bone":52,"x":0,"y":0,"z":65},{"bone":54,"x":0,"y":0,"z":30},{"bone":56,"x":0,"y":-3,"z":0},{"bone":58,"x":-8,"y":0,"z":0}]},
    {"frameId":9,"transformCount":59,"transforms":[{"bone":1,"x":0,"y":31,"z":0},{"bone":4,"x":-11,"y":-17,"z":-10},{"bone":6,"x":5,"y":-11,"z":0},{"bone":8,"x":0,"y":14,"z":14},{"bone":10,"x":0,"y":0,"z":-46},{"bone":12,"x":0,"y":0,"z":-12},{"bone":14,"x":0,"y":3,"z":22},{"bone":16,"x":0,"y":0,"z":-55},{"bone":18,"x":0,"y":0,"z":-29},{"bone":20,"x":0,"y":-2,"z":19},{"bone":22,"x":0,"y":0,"z":-45},{"bone":24,"x":0,"y":0,"z":-29},{"bone":26,"x":0,"y":-11,"z":27},{"bone":28,"x":0,"y":0,"z":-51},{"bone":30,"x":0,"y":0,"z":-29},{"bone":32,"x":0,"y":-10,"z":-12},{"bone":34,"x":0,"y":0,"z":44},{"bone":36,"x":0,"y":0,"z":28},{"bone":38,"x":0,"y":-2,"z":-14},{"bone":40,"x":0,"y":0,"z":43},{"bone":42,"x":0,"y":0,"z":30},{"bone":44,"x":0,"y":3,"z":-15},{"bone":46,"x":0,"y":0,"z":44},{"bone":48,"x":0,"y":0,"z":30},{"bone":50,"x":0,"y":9,"z":-21},{"bone":52,"x":0,"y":0,"z":47},{"bone":54,"x":0,"y":0,"z":30},{"bone":56,"x":0,"y":2,"z":0},{"bone":58,"x":-5,"y":0,"z":0}]},
    {"frameId":10,"transformCount":59,"transforms":[{"bone":1,"x":0,"y":35,"z":0},{"bone":4,"x":-11,"y":-17,"z":-10},{"bone":6,"x":5,"y":-11,"z":0},{"bone":8,"x":0,"y":17,"z":11},{"bone":10,"x":0,"y":0,"z":-37},{"bone":12,"x":0,"y":0,"z":-5},{"bone":14,"x":0,"y":3,"z":21},{"bone":16,"x":0,"y":0,"z":-50},{"bone":18,"x":0,"y":0,"z":-29},{"bone":20,"x":0,"y":-2,"z":16},{"bone":22,"x":0,"y":0,"z":-35},{"bone":24,"x":0,"y":0,"z":-29},{"bone":26,"x":0,"y":-13,"z":25},{"bone":28,"x":0,"y":0,"z":-45},{"bone":30,"x":0,"y":0,"z":-29},{"bone":32,"x":0,"y":-12,"z":-8},{"bone":34,"x":0,"y":0,"z":33},{"bone":36,"x":0,"y":0,"z":28},{"bone":38,"x":0,"y":-2,"z":-10},{"bone":40,"x":0,"y":0,"z":32},{"bone":42,"x":0,"y":0,"z":30},{"bone":44,"x":0,"y":3,"z":-11},{"bone":46,"x":0,"y":0,"z":34},{"bone":48,"x":0,"y":0,"z":30},{"bone":50,"x":0,"y":10,"z":-17},{"bone":52,"x":0,"y":0,"z":38},{"bone":54,"x":0,"y":0,"z":30},{"bone":56,"x":0,"y":5,"z":0},{"bone":58,"x":-4,"y":0,"z":0}]},
    {"frameId":11,"transformCount":59,"transforms":[{"bone":1,"x":0,"y":40,"z":0},{"bone":4,"x":-11,"y":-17,"z":-10},{"bone":6,"x":5,"y":-11,"z":0},{"bone":8,"x":0,"y":20,"z":9},{"bone":10,"x":0,"y":0,"z":-29},{"bone":12,"x":0,"y":0,"z":1},{"bone":14,"x":0,"y":3,"z":21},{"bone":16,"x":0,"y":0,"z":-46},{"bone":18,"x":0,"y":0,"z":-29},{"bone":20,"x":0,"y":-2,"z":13},{"bone":22,"x":0,"y":0,"z":-26},{"bone":24,"x":0,"y":0,"z":-29},{"bone":26,"x":0,"y":-15,"z":24},{"bone":28,"x":0,"y":0,"z":-39},{"bone":30,"x":0,"y":0,"z":-29},{"bone":32,"x":0,"y":-14,"z":-5},{"bone":34,"x":0,"y":0,"z":23},{"bone":36,"x":0,"y":0,"z":28},{"bone":38,"x":0,"y":-2,"z":-6},{"bone":40,"x":0,"y":0,"z":22},{"bone":42,"x":0,"y":0,"z":30},{"bone":44,"x":0,"y":3,"z":-7},{"bone":46,"x":0,"y":0,"z":24},{"bone":48,"x":0,"y":0,"z":30},{"bone":50,"x":0,"y":12,"z":-13},{"bone":52,"x":0,"y":0,"z":29},{"bone":54,"x":0,"y":0,"z":30},{"bone":56,"x":0,"y":9,"z":0},{"bone":58,"x":-3,"y":0,"z":0}]},
    {"frameId":12,"transformCount":59,"transforms":[{"bone":1,"x":0,"y":40,"z":0},{"bone":4,"x":-8,"y":-15,"z":-9},{"bone":6,"x":26,"y":-6,"z":0},{"bone":8,"x":0,"y":20,"z":9},{"bone":10,"x":0,"y":0,"z":-29},{"bone":12,"x":0,"y":0,"z":1},{"bone":14,"x":0,"y":3,"z":21},{"bone":16,"x":0,"y":0,"z":-46},{"bone":18,"x":0,"y":0,"z":-29},{"bone":20,"x":0,"y":-2,"z":13},{"bone":22,"x":0,"y":0,"z":-26},{"bone":24,"x":0,"y":0,"z":-29},{"bone":26,"x":0,"y":-15,"z":24},{"bone":28,"x":0,"y":0,"z":-39},{"bone":30,"x":0,"y":0,"z":-29},{"bone":32,"x":0,"y":-14,"z":-5},{"bone":34,"x":0,"y":0,"z":23},{"bone":36,"x":0,"y":0,"z":28},{"bone":38,"x":0,"y":-2,"z":-6},{"bone":40,"x":0,"y":0,"z":22},{"bone":42,"x":0,"y":0,"z":30},{"bone":44,"x":0,"y":3,"z":-7},{"bone":46,"x":0,"y":0,"z":24},{"bone":48,"x":0,"y":0,"z":30},{"bone":50,"x":0,"y":12,"z":-13},{"bone":52,"x":0,"y":0,"z":29},{"bone":54,"x":0,"y":0,"z":30},{"bone":56,"x":0,"y":9,"z":0},{"bone":58,"x":-3,"y":0,"z":0}]},
    {"frameId":13,"transformCount":59,"transforms":[{"bone":1,"x":0,"y":40,"z":0},{"bone":4,"x":-6,"y":-14,"z":-8},{"bone":6,"x":47,"y":-2,"z":0},{"bone":8,"x":0,"y":20,"z":9},{"bone":10,"x":0,"y":0,"z":-29},{"bone":12,"x":0,"y":0,"z":1},{"bone":14,"x":0,"y":3,"z":21},{"bone":16,"x":0,"y":0,"z":-46},{"bone":18,"x":0,"y":0,"z":-29},{"bone":20,"x":0,"y":-2,"z":13},{"bone":22,"x":0,"y":0,"z":-26},{"bone":24,"x":0,"y":0,"z":-29},{"bone":26,"x":0,"y":-15,"z":24},{"bone":28,"x":0,"y":0,"z":-39},{"bone":30,"x":0,"y":0,"z":-29},{"bone":32,"x":0,"y":-14,"z":-5},{"bone":34,"x":0,"y":0,"z":23},{"bone":36,"x":0,"y":0,"z":28},{"bone":38,"x":0,"y":-2,"z":-6},{"bone":40,"x":0,"y":0,"z":22},{"bone":42,"x":0,"y":0,"z":30},{"bone":44,"x":0,"y":3,"z":-7},{"bone":46,"x":0,"y":0,"z":24},{"bone":48,"x":0,"y":0,"z":30},{"bone":50,"x":0,"y":12,"z":-13},{"bone":52,"x":0,"y":0,"z":29},{"bone":54,"x":0,"y":0,"z":30},{"bone":56,"x":0,"y":9,"z":0},{"bone":58,"x":-3,"y":0,"z":0}]},
    {"frameId":14,"transformCount":59,"transforms":[{"bone":1,"x":0,"y":40,"z":0},{"bone":4,"x":-4,"y":-13,"z":-7},{"bone":6,"x":68,"y":1,"z":0},{"bone":8,"x":0,"y":20,"z":9},{"bone":10,"x":0,"y":0,"z":-29},{"bone":12,"x":0,"y":0,"z":1},{"bone":14,"x":0,"y":3,"z":21},{"bone":16,"x":0,"y":0,"z":-46},{"bone":18,"x":0,"y":0,"z":-29},{"bone":20,"x":0,"y":-2,"z":13},{"bone":22,"x":0,"y":0,"z":-26},{"bone":24,"x":0,"y":0,"z":-29},{"bone":26,"x":0,"y":-15,"z":24},{"bone":28,"x":0,"y":0,"z":-39},{"bone":30,"x":0,"y":0,"z":-29},{"bone":32,"x":0,"y":-14,"z":-5},{"bone":34,"x":0,"y":0,"z":23},{"bone":36,"x":0,"y":0,"z":28},{"bone":38,"x":0,"y":-2,"z":-6},{"bone":40,"x":0,"y":0,"z":22},{"bone":42,"x":0,"y":0,"z":30},{"bone":44,"x":0,"y":3,"z":-7},{"bone":46,"x":0,"y":0,"z":24},{"bone":48,"x":0,"y":0,"z":30},{"bone":50,"x":0,"y":12,"z":-13},{"bone":52,"x":0,"y":0,"z":29},{"bone":54,"x":0,"y":0,"z":30},{"bone":56,"x":0,"y":9,"z":0},{"bone":58,"x":-3,"y":0,"z":0}]},
    {"frameId":15,"transformCount":57,"transforms":[{"bone":1,"x":0,"y":23,"z":0},{"bone":8,"x":0,"y":8,"z":25},{"bone":10,"x":0,"y":0,"z":-64},{"bone":12,"x":0,"y":0,"z":-27},{"bone":14,"x":0,"y":3,"z":25},{"bone":16,"x":0,"y":0,"z":-64},{"bone":18,"x":0,"y":0,"z":-29},{"bone":20,"x":0,"y":-2,"z":25},{"bone":22,"x":0,"y":0,"z":-64},{"bone":24,"x":0,"y":0,"z":-29},{"bone":26,"x":0,"y":-7,"z":25},{"bone":28,"x":0,"y":0,"z":-64},{"bone":30,"x":0,"y":0,"z":-29},{"bone":32,"x":0,"y":-7,"z":-24},{"bone":34,"x":0,"y":0,"z":65},{"bone":36,"x":0,"y":0,"z":28},{"bone":38,"x":0,"y":-2,"z":-24},{"bone":40,"x":0,"y":0,"z":65},{"bone":42,"x":0,"y":0,"z":30},{"bone":44,"x":0,"y":3,"z":-24},{"bone":46,"x":0,"y":0,"z":65},{"bone":48,"x":0,"y":0,"z":30},{"bone":50,"x":0,"y":6,"z":-24},{"bone":52,"x":0,"y":0,"z":65},{"bone":54,"x":0,"y":0,"z":30},{"bone":56,"x":0,"y":-3,"z":0}]},
    {"frameId":16,"transformCount":59,"transforms":[{"bone":1,"x":0,"y":23,"z":0},{"bone":4,"x":-2,"y":-3,"z":-1},{"bone":6,"x":1,"y":-2,"z":0},{"bone":8,"x":0,"y":8,"z":23},{"bone":10,"x":0,"y":0,"z":-64},{"bone":12,"x":0,"y":0,"z":-27},{"bone":14,"x":0,"y":3,"z":24},{"bone":16,"x":0,"y":0,"z":-64},{"bone":18,"x":0,"y":0,"z":-29},{"bone":20,"x":0,"y":-2,"z":25},{"bone":22,"x":0,"y":0,"z":-64},{"bone":24,"x":0,"y":0,"z":-29},{"bone":26,"x":0,"y":-7,"z":26},{"bone":28,"x":0,"y":0,"z":-64},{"bone":30,"x":0,"y":0,"z":-29},{"bone":32,"x":0,"y":-7,"z":-22},{"bone":34,"x":0,"y":0,"z":65},{"bone":36,"x":0,"y":0,"z":28},{"bone":38,"x":0,"y":-2,"z":-23},{"bone":40,"x":0,"y":0,"z":65},{"bone":42,"x":0,"y":0,"z":30},{"bone":44,"x":0,"y":3,"z":-24},{"bone":46,"x":0,"y":0,"z":65},{"bone":48,"x":0,"y":0,"z":30},{"bone":50,"x":0,"y":6,"z":-25},{"bone":52,"x":0,"y":0,"z":65},{"bone":54,"x":0,"y":0,"z":30},{"bone":56,"x":0,"y":-3,"z":0},{"bone":58,"x":-1,"y":0,"z":0}]},
    {"frameId":17,"transformCount":59,"transforms":[{"bone":1,"x":0,"y":23,"z":0},{"bone":4,"x":-5,"y":-8,"z":-4},{"bone":6,"x":2,"y":-5,"z":0},{"bone":8,"x":0,"y":8,"z":22},{"bone":10,"x":0,"y":0,"z":-64},{"bone":12,"x":0,"y":0,"z":-27},{"bone":14,"x":0,"y":3,"z":24},{"bone":16,"x":0,"y":0,"z":-64},{"bone":18,"x":0,"y":0,"z":-29},{"bone":20,"x":0,"y":-2,"z":25},{"bone":22,"x":0,"y":0,"z":-64},{"bone":24,"x":0,"y":0,"z":-29},{"bone":26,"x":0,"y":-7,"z":27},{"bone":28,"x":0,"y":0,"z":-64},{"bone":30,"x":0,"y":0,"z":-29},{"bone":32,"x":0,"y":-7,"z":-21},{"bone":34,"x":0,"y":0,"z":65},{"bone":36,"x":0,"y":0,"z":28},{"bone":38,"x":0,"y":-2,"z":-23},{"bone":40,"x":0,"y":0,"z":65},{"bone":42,"x":0,"y":0,"z":30},{"bone":44,"x":0,"y":3,"z":-24},{"bone":46,"x":0,"y":0,"z":65},{"bone":48,"x":0,"y":0,"z":30},{"bone":50,"x":0,"y":6,"z":-26},{"bone":52,"x":0,"y":0,"z":65},{"bone":54,"x":0,"y":0,"z":30},{"bone":56,"x":0,"y":-3,"z":0},{"bone":58,"x":-3,"y":0,"z":0}]},
    {"frameId":18,"transformCount":59,"transforms":[{"bone":1,"x":0,"y":23,"z":0},{"bone":4,"x":-8,"y":-12,"z":-7},{"bone":6,"x":3,"y":-8,"z":0},{"bone":8,"x":0,"y":8,"z":21},{"bone":10,"x":0,"y":0,"z":-64},{"bone":12,"x":0,"y":0,"z":-27},{"bone":14,"x":0,"y":3,"z":24},{"bone":16,"x":0,"y":0,"z":-64},{"bone":18,"x":0,"y":0,"z":-29},{"bone":20,"x":0,"y":-2,"z":25},{"bone":22,"x":0,"y":0,"z":-64},{"bone":24,"x":0,"y":0,"z":-29},{"bone":26,"x":0,"y":-7,"z":28},{"bone":28,"x":0,"y":0,"z":-64},{"bone":30,"x":0,"y":0,"z":-29},{"bone":32,"x":0,"y":-7,"z":-20},{"bone":34,"x":0,"y":0,"z":65},{"bone":36,"x":0,"y":0,"z":28},{"bone":38,"x":0,"y":-2,"z":-23},{"bone":40,"x":0,"y":0,"z":65},{"bone":42,"x":0,"y":0,"z":30},{"bone":44,"x":0,"y":3,"z":-24},{"bone":46,"x":0,"y":0,"z":65},{"bone":48,"x":0,"y":0,"z":30},{"bone":50,"x":0,"y":6,"z":-27},{"bone":52,"x":0,"y":0,"z":65},{"bone":54,"x":0,"y":0,"z":30},{"bone":56,"x":0,"y":-3,"z":0},{"bone":58,"x":-5,"y":0,"z":0}]},
    {"frameId":19,"transformCount":59,"transforms":[{"bone":1,"x":0,"y":23,"z":0},{"bone":4,"x":-11,"y":-17,"z":-10},{"bone":6,"x":5,"y":-11,"z":0},{"bone":8,"x":0,"y":8,"z":20},{"bone":10,"x":0,"y":0,"z":-64},{"bone":12,"x":0,"y":0,"z":-27},{"bone":14,"x":0,"y":3,"z":24},{"bone":16,"x":0,"y":0,"z":-64},{"bone":18,"x":0,"y":0,"z":-29},{"bone":20,"x":0,"y":-2,"z":25},{"bone":22,"x":0,"y":0,"z":-64},{"bone":24,"x":0,"y":0,"z":-29},{"bone":26,"x":0,"y":-7,"z":30},{"bone":28,"x":0,"y":0,"z":-64},{"bone":30,"x":0,"y":0,"z":-29},{"bone":32,"x":0,"y":-7,"z":-19},{"bone":34,"x":0,"y":0,"z":65},{"bone":36,"x":0,"y":0,"z":28},{"bone":38,"x":0,"y":-2,"z":-23},{"bone":40,"x":0,"y":0,"z":65},{"bone":42,"x":0,"y":0,"z":30},{"bone":44,"x":0,"y":3,"z":-24},{"bone":46,"x":0,"y":0,"z":65},{"bone":48,"x":0,"y":0,"z":30},{"bone":50,"x":0,"y":6,"z":-29},{"bone":52,"x":0,"y":0,"z":65},{"bone":54,"x":0,"y":0,"z":30},{"bone":56,"x":0,"y":-3,"z":0},{"bone":58,"x":-8,"y":0,"z":0}]},
    {"frameId":20,"transformCount":57,"transforms":[{"bone":1,"x":0,"y":23,"z":0},{"bone":8,"x":0,"y":8,"z":25},{"bone":10,"x":0,"y":0,"z":-64},{"bone":12,"x":0,"y":0,"z":-27},{"bone":14,"x":0,"y":3,"z":25},{"bone":16,"x":0,"y":0,"z":-64},{"bone":18,"x":0,"y":0,"z":-29},{"bone":20,"x":0,"y":-2,"z":25},{"bone":22,"x":0,"y":0,"z":-64},{"bone":24,"x":0,"y":0,"z":-29},{"bone":26,"x":0,"y":-7,"z":25},{"bone":28,"x":0,"y":0,"z":-64},{"bone":30,"x":0,"y":0,"z":-29},{"bone":32,"x":0,"y":-7,"z":-24},{"bone":34,"x":0,"y":0,"z":65},{"bone":36,"x":0,"y":0,"z":28},{"bone":38,"x":0,"y":-2,"z":-24},{"bone":40,"x":0,"y":0,"z":65},{"bone":42,"x":0,"y":0,"z":30},{"bone":44,"x":0,"y":3,"z":-24},{"bone":46,"x":0,"y":0,"z":65},{"bone":48,"x":0,"y":0,"z":30},{"bone":50,"x":0,"y":6,"z":-24},{"bone":52,"x":0,"y":0,"z":65},{"bone":54,"x":0,"y":0,"z":30},{"bone":56,"x":0,"y":-3,"z":0}]},
    {"frameId":21,"transformCount":57,"transforms":[{"bone":1,"x":0,"y":23,"z":0},{"bone":8,"x":0,"y":8,"z":25},{"bone":10,"x":0,"y":0,"z":-64},{"bone":12,"x":0,"y":0,"z":-27},{"bone":14,"x":0,"y":3,"z":25},{"bone":16,"x":0,"y":0,"z":-64},{"bone":18,"x":0,"y":0,"z":-29},{"bone":20,"x":0,"y":-2,"z":25},{"bone":22,"x":0,"y":0,"z":-64},{"bone":24,"x":0,"y":0,"z":-29},{"bone":26,"x":0,"y":-7,"z":25},{"bone":28,"x":0,"y":0,"z":-64},{"bone":30,"x":0,"y":0,"z":-29},{"bone":32,"x":0,"y":-7,"z":-24},{"bone":34,"x":0,"y":0,"z":65},{"bone":36,"x":0,"y":0,"z":28},{"bone":38,"x":0,"y":-2,"z":-24},{"bone":40,"x":0,"y":0,"z":65},{"bone":42,"x":0,"y":0,"z":30},{"bone":44,"x":0,"y":3,"z":-24},{"bone":46,"x":0,"y":0,"z":65},{"bone":48,"x":0,"y":0,"z":30},{"bone":50,"x":0,"y":6,"z":-24},{"bone":52,"x":0,"y":0,"z":65},{"bone":54,"x":0,"y":0,"z":30},{"bone":56,"x":0,"y":-1,"z":0}]},
    {"frameId":22,"transformCount":55,"transforms":[{"bone":1,"x":0,"y":23,"z":0},{"bone":8,"x":0,"y":8,"z":25},{"bone":10,"x":0,"y":0,"z":-64},{"bone":12,"x":0,"y":0,"z":-27},{"bone":14,"x":0,"y":3,"z":25},{"bone":16,"x":0,"y":0,"z":-64},{"bone":18,"x":0,"y":0,"z":-29},{"bone":20,"x":0,"y":-2,"z":25},{"bone":22,"x":0,"y":0,"z":-64},{"bone":24,"x":0,"y":0,"z":-29},{"bone":26,"x":0,"y":-7,"z":25},{"bone":28,"x":0,"y":0,"z":-64},{"bone":30,"x":0,"y":0,"z":-29},{"bone":32,"x":0,"y":-7,"z":-24},{"bone":34,"x":0,"y":0,"z":65},{"bone":36,"x":0,"y":0,"z":28},{"bone":38,"x":0,"y":-2,"z":-24},{"bone":40,"x":0,"y":0,"z":65},{"bone":42,"x":0,"y":0,"z":30},{"bone":44,"x":0,"y":3,"z":-24},{"bone":46,"x":0,"y":0,"z":65},{"bone":48,"x":0,"y":0,"z":30},{"bone":50,"x":0,"y":6,"z":-24},{"bone":52,"x":0,"y":0,"z":65},{"bone":54,"x":0,"y":0,"z":30}]},
    {"frameId":23,"transformCount":57,"transforms":[{"bone":1,"x":0,"y":23,"z":0},{"bone":8,"x":0,"y":8,"z":25},{"bone":10,"x":0,"y":0,"z":-64},{"bone":12,"x":0,"y":0,"z":-27},{"bone":14,"x":0,"y":3,"z":25},{"bone":16,"x":0,"y":0,"z":-64},{"bone":18,"x":0,"y":0,"z":-29},{"bone":20,"x":0,"y":-2,"z":25},{"bone":22,"x":0,"y":0,"z":-64},{"bone":24,"x":0,"y":0,"z":-29},{"bone":26,"x":0,"y":-7,"z":25},{"bone":28,"x":0,"y":0,"z":-64},{"bone":30,"x":0,"y":0,"z":-29},{"bone":32,"x":0,"y":-7,"z":-24},{"bone":34,"x":0,"y":0,"z":65},{"bone":36,"x":0,"y":0,"z":28},{"bone":38,"x":0,"y":-2,"z":-24},{"bone":40,"x":0,"y":0,"z":65},{"bone":42,"x":0,"y":0,"z":30},{"bone":44,"x":0,"y":3,"z":-24},{"bone":46,"x":0,"y":0,"z":65},{"bone":48,"x":0,"y":0,"z":30},{"bone":50,"x":0,"y":6,"z":-24},{"bone":52,"x":0,"y":0,"z":65},{"bone":54,"x":0,"y":0,"z":30},{"bone":56,"x":0,"y":2,"z":0}]},
    {"frameId":24,"transformCount":57,"transforms":[{"bone":1,"x":0,"y":23,"z":0},{"bone":8,"x":0,"y":8,"z":25},{"bone":10,"x":0,"y":0,"z":-64},{"bone":12,"x":0,"y":0,"z":-27},{"bone":14,"x":0,"y":3,"z":25},{"bone":16,"x":0,"y":0,"z":-64},{"bone":18,"x":0,"y":0,"z":-29},{"bone":20,"x":0,"y":-2,"z":25},{"bone":22,"x":0,"y":0,"z":-64},{"bone":24,"x":0,"y":0,"z":-29},{"bone":26,"x":0,"y":-7,"z":25},{"bone":28,"x":0,"y":0,"z":-64},{"bone":30,"x":0,"y":0,"z":-29},{"bone":32,"x":0,"y":-7,"z":-24},{"bone":34,"x":0,"y":0,"z":65},{"bone":36,"x":0,"y":0,"z":28},{"bone":38,"x":0,"y":-2,"z":-24},{"bone":40,"x":0,"y":0,"z":65},{"bone":42,"x":0,"y":0,"z":30},{"bone":44,"x":0,"y":3,"z":-24},{"bone":46,"x":0,"y":0,"z":65},{"bone":48,"x":0,"y":0,"z":30},{"bone":50,"x":0,"y":6,"z":-24},{"bone":52,"x":0,"y":0,"z":65},{"bone":54,"x":0,"y":0,"z":30},{"bone":56,"x":0,"y":4,"z":0}]},
    {"frameId":25,"transformCount":57,"transforms":[{"bone":1,"x":0,"y":23,"z":0},{"bone":8,"x":0,"y":20,"z":30},{"bone":10,"x":0,"y":0,"z":-67},{"bone":12,"x":0,"y":16,"z":-6},{"bone":14,"x":0,"y":3,"z":25},{"bone":16,"x":0,"y":0,"z":-64},{"bone":18,"x":0,"y":0,"z":-27},{"bone":20,"x":0,"y":-6,"z":37},{"bone":22,"x":0,"y":0,"z":-76},{"bone":24,"x":0,"y":0,"z":-49},{"bone":26,"x":0,"y":-9,"z":35},{"bone":28,"x":0,"y":0,"z":-66},{"bone":30,"x":0,"y":0,"z":-27},{"bone":32,"x":0,"y":-19,"z":-36},{"bone":34,"x":0,"y":0,"z":77},{"bone":36,"x":0,"y":0,"z":50},{"bone":38,"x":0,"y":-2,"z":-34},{"bone":40,"x":0,"y":0,"z":67},{"bone":42,"x":0,"y":0,"z":28},{"bone":44,"x":0,"y":7,"z":-29},{"bone":46,"x":0,"y":0,"z":68},{"bone":48,"x":0,"y":0,"z":7},{"bone":50,"x":0,"y":10,"z":-24},{"bone":52,"x":0,"y":0,"z":65},{"bone":54,"x":0,"y":0,"z":28},{"bone":56,"x":0,"y":-3,"z":0}]},
    {"frameId":26,"transformCount":57,"transforms":[{"bone":1,"x":0,"y":23,"z":0},{"bone":8,"x":0,"y":15,"z":27},{"bone":10,"x":0,"y":0,"z":-65},{"bone":12,"x":0,"y":8,"z":-16},{"bone":14,"x":0,"y":1,"z":31},{"bone":16,"x":0,"y":0,"z":-70},{"bone":18,"x":0,"y":0,"z":-38},{"bone":20,"x":0,"y":-4,"z":36},{"bone":22,"x":0,"y":0,"z":-71},{"bone":24,"x":0,"y":0,"z":-38},{"bone":26,"x":0,"y":-10,"z":32},{"bone":28,"x":0,"y":0,"z":-66},{"bone":30,"x":0,"y":0,"z":-16},{"bone":32,"x":0,"y":-14,"z":-35},{"bone":34,"x":0,"y":0,"z":72},{"bone":36,"x":0,"y":0,"z":39},{"bone":38,"x":0,"y":-4,"z":-31},{"bone":40,"x":0,"y":0,"z":67},{"bone":42,"x":0,"y":0,"z":17},{"bone":44,"x":0,"y":5,"z":-26},{"bone":46,"x":0,"y":0,"z":66},{"bone":48,"x":0,"y":0,"z":17},{"bone":50,"x":0,"y":8,"z":-30},{"bone":52,"x":0,"y":0,"z":71},{"bone":54,"x":0,"y":0,"z":39},{"bone":56,"x":0,"y":-3,"z":0}]},
    {"frameId":27,"transformCount":57,"transforms":[{"bone":1,"x":0,"y":23,"z":0},{"bone":8,"x":0,"y":10,"z":25},{"bone":10,"x":0,"y":0,"z":-64},{"bone":12,"x":0,"y":0,"z":-27},{"bone":14,"x":0,"y":0,"z":37},{"bone":16,"x":0,"y":0,"z":-76},{"bone":18,"x":0,"y":0,"z":-49},{"bone":20,"x":0,"y":-2,"z":35},{"bone":22,"x":0,"y":0,"z":-66},{"bone":24,"x":0,"y":0,"z":-27},{"bone":26,"x":0,"y":-11,"z":30},{"bone":28,"x":0,"y":0,"z":-67},{"bone":30,"x":0,"y":0,"z":-6},{"bone":32,"x":0,"y":-9,"z":-34},{"bone":34,"x":0,"y":0,"z":67},{"bone":36,"x":0,"y":0,"z":28},{"bone":38,"x":0,"y":-6,"z":-29},{"bone":40,"x":0,"y":0,"z":68},{"bone":42,"x":0,"y":0,"z":7},{"bone":44,"x":0,"y":3,"z":-24},{"bone":46,"x":0,"y":0,"z":65},{"bone":48,"x":0,"y":0,"z":28},{"bone":50,"x":0,"y":6,"z":-36},{"bone":52,"x":0,"y":0,"z":77},{"bone":54,"x":0,"y":0,"z":50},{"bone":56,"x":0,"y":-3,"z":0}]},
    {"frameId":28,"transformCount":57,"transforms":[{"bone":1,"x":0,"y":23,"z":0},{"bone":8,"x":0,"y":8,"z":31},{"bone":10,"x":0,"y":0,"z":-70},{"bone":12,"x":0,"y":0,"z":-38},{"bone":14,"x":0,"y":1,"z":36},{"bone":16,"x":0,"y":0,"z":-71},{"bone":18,"x":0,"y":0,"z":-38},{"bone":20,"x":0,"y":0,"z":32},{"bone":22,"x":0,"y":0,"z":-66},{"bone":24,"x":0,"y":0,"z":-16},{"bone":26,"x":0,"y":-10,"z":27},{"bone":28,"x":0,"y":0,"z":-65},{"bone":30,"x":0,"y":0,"z":-16},{"bone":32,"x":0,"y":-7,"z":-31},{"bone":34,"x":0,"y":0,"z":67},{"bone":36,"x":0,"y":0,"z":17},{"bone":38,"x":0,"y":-4,"z":-26},{"bone":40,"x":0,"y":0,"z":66},{"bone":42,"x":0,"y":0,"z":17},{"bone":44,"x":0,"y":1,"z":-30},{"bone":46,"x":0,"y":0,"z":71},{"bone":48,"x":0,"y":0,"z":39},{"bone":50,"x":0,"y":8,"z":-35},{"bone":52,"x":0,"y":0,"z":72},{"bone":54,"x":0,"y":0,"z":39},{"bone":56,"x":0,"y":-3,"z":0}]},
    {"frameId":29,"transformCount":57,"transforms":[{"bone":1,"x":0,"y":23,"z":0},{"bone":8,"x":0,"y":6,"z":37},{"bone":10,"x":0,"y":0,"z":-76},{"bone":12,"x":0,"y":0,"z":-49},{"bone":14,"x":0,"y":3,"z":35},{"bone":16,"x":0,"y":0,"z":-66},{"bone":18,"x":0,"y":0,"z":-27},{"bone":20,"x":0,"y":0,"z":30},{"bone":22,"x":0,"y":0,"z":-67},{"bone":24,"x":0,"y":0,"z":-6},{"bone":26,"x":0,"y":-9,"z":25},{"bone":28,"x":0,"y":0,"z":-64},{"bone":30,"x":0,"y":0,"z":-27},{"bone":32,"x":0,"y":-5,"z":-29},{"bone":34,"x":0,"y":0,"z":68},{"bone":36,"x":0,"y":0,"z":7},{"bone":38,"x":0,"y":-2,"z":-24},{"bone":40,"x":0,"y":0,"z":65},{"bone":42,"x":0,"y":0,"z":28},{"bone":44,"x":0,"y":0,"z":-36},{"bone":46,"x":0,"y":0,"z":77},{"bone":48,"x":0,"y":0,"z":50},{"bone":50,"x":0,"y":10,"z":-34},{"bone":52,"x":0,"y":0,"z":67},{"bone":54,"x":0,"y":0,"z":28},{"bone":56,"x":0,"y":-3,"z":0}]},
    {"frameId":30,"transformCount":57,"transforms":[{"bone":1,"x":0,"y":23,"z":0},{"bone":8,"x":0,"y":8,"z":36},{"bone":10,"x":0,"y":0,"z":-70},{"bone":12,"x":0,"y":0,"z":-38},{"bone":14,"x":0,"y":5,"z":32},{"bone":16,"x":0,"y":0,"z":-66},{"bone":18,"x":0,"y":0,"z":-16},{"bone":20,"x":0,"y":0,"z":27},{"bone":22,"x":0,"y":0,"z":-65},{"bone":24,"x":0,"y":0,"z":-16},{"bone":26,"x":0,"y":-7,"z":31},{"bone":28,"x":0,"y":0,"z":-70},{"bone":30,"x":0,"y":0,"z":-38},{"bone":32,"x":0,"y":-7,"z":-26},{"bone":34,"x":0,"y":0,"z":66},{"bone":36,"x":0,"y":0,"z":17},{"bone":38,"x":0,"y":0,"z":-30},{"bone":40,"x":0,"y":0,"z":71},{"bone":42,"x":0,"y":0,"z":39},{"bone":44,"x":0,"y":1,"z":-35},{"bone":46,"x":0,"y":0,"z":72},{"bone":48,"x":0,"y":0,"z":39},{"bone":50,"x":0,"y":11,"z":-31},{"bone":52,"x":0,"y":0,"z":67},{"bone":54,"x":0,"y":0,"z":17},{"bone":56,"x":0,"y":-3,"z":0}]},
    {"frameId":31,"transformCount":57,"transforms":[{"bone":1,"x":0,"y":23,"z":0},{"bone":8,"x":0,"y":10,"z":35},{"bone":10,"x":0,"y":0,"z":-64},{"bone":12,"x":0,"y":0,"z":-27},{"bone":14,"x":0,"y":7,"z":30},{"bone":16,"x":0,"y":0,"z":-67},{"bone":18,"x":0,"y":0,"z":-6},{"bone":20,"x":0,"y":-2,"z":25},{"bone":22,"x":0,"y":0,"z":-64},{"bone":24,"x":0,"y":0,"z":-27},{"bone":26,"x":0,"y":-5,"z":37},{"bone":28,"x":0,"y":0,"z":-76},{"bone":30,"x":0,"y":0,"z":-49},{"bone":32,"x":0,"y":-9,"z":-24},{"bone":34,"x":0,"y":0,"z":65},{"bone":36,"x":0,"y":0,"z":28},{"bone":38,"x":0,"y":0,"z":-36},{"bone":40,"x":0,"y":0,"z":77},{"bone":42,"x":0,"y":0,"z":50},{"bone":44,"x":0,"y":3,"z":-34},{"bone":46,"x":0,"y":0,"z":67},{"bone":48,"x":0,"y":0,"z":28},{"bone":50,"x":0,"y":12,"z":-29},{"bone":52,"x":0,"y":0,"z":68},{"bone":54,"x":0,"y":0,"z":7},{"bone":56,"x":0,"y":-3,"z":0}]},
    {"frameId":32,"transformCount":57,"transforms":[{"bone":1,"x":0,"y":23,"z":0},{"bone":8,"x":0,"y":15,"z":32},{"bone":10,"x":0,"y":0,"z":-65},{"bone":12,"x":0,"y":8,"z":-16},{"bone":14,"x":0,"y":5,"z":27},{"bone":16,"x":0,"y":0,"z":-65},{"bone":18,"x":0,"y":0,"z":-16},{"bone":20,"x":0,"y":-4,"z":31},{"bone":22,"x":0,"y":0,"z":-70},{"bone":24,"x":0,"y":0,"z":-38},{"bone":26,"x":0,"y":-7,"z":36},{"bone":28,"x":0,"y":0,"z":-71},{"bone":30,"x":0,"y":0,"z":-38},{"bone":32,"x":0,"y":-14,"z":-30},{"bone":34,"x":0,"y":0,"z":71},{"bone":36,"x":0,"y":0,"z":39},{"bone":38,"x":0,"y":0,"z":-35},{"bone":40,"x":0,"y":0,"z":72},{"bone":42,"x":0,"y":0,"z":39},{"bone":44,"x":0,"y":5,"z":-31},{"bone":46,"x":0,"y":0,"z":67},{"bone":48,"x":0,"y":0,"z":17},{"bone":50,"x":0,"y":11,"z":-26},{"bone":52,"x":0,"y":0,"z":66},{"bone":54,"x":0,"y":0,"z":17},{"bone":56,"x":0,"y":-3,"z":0}]}
  ]
}
