{
  "skinList": {
    "boneCount": 16,
    "transformTypes": [0,2,1,5,0,2,1,5,0,2,1,5,0,2,1,5],
    "childIndices": [[0],[0],[0],[0],[1],[1],[1],[1],[2],[2],[2],[2],[3],[3],[3],[3]]
  },
  "frameCount": 6,
  "frames": [
    {"frameId":0,"transformCount":5,"transforms":[{"bone":0,"x":0,"y":0,"z":-21},{"bone":4,"x":0,"y":0,"z":30}]},
    {"frameId":1,"transformCount":15,"transforms":[{"bone":0,"x":0,"y":0,"z":-21},{"bone":1,"x":-25,"y":0,"z":0},{"bone":4,"x":0,"y":0,"z":30},{"bone":5,"x":25,"y":0,"z":0},{"bone":9,"x":0,"y":-21,"z":11},{"bone":10,"x":0,"y":37,"z":0},{"bone":13,"x":10,"y":63,"z":-6},{"bone":14,"x":0,"y":51,"z":0}]},
    {"frameId":2,"transformCount":15,"transforms":[{"bone":0,"x":0,"y":0,"z":-21},{"bone":1,"x":-51,"y":0,"z":0},{"bone":4,"x":0,"y":0,"z":30},{"bone":5,"x":51,"y":0,"z":0},{"bone":9,"x":0,"y":-43,"z":23},{"bone":10,"x":0,"y":74,"z":0},{"bone":13,"x":21,"y":127,"z":-14},{"bone":14,"x":0,"y":103,"z":0}]},
    {"frameId":3,"transformCount":16,"transforms":[{"bone":0,"x":0,"y":0,"z":-21},{"bone":1,"x":-51,"y":0,"z":0},{"bone":3,"x":7,"y":0,"z":0},{"bone":4,"x":0,"y":0,"z":30},{"bone":5,"x":51,"y":0,"z":0},{"bone":7,"x":8,"y":0,"z":0},{"bone":9,"x":0,"y":-43,"z":23},{"bone":10,"x":0,"y":81,"z":0},{"bone":11,"x":7,"y":0,"z":0},{"bone":13,"x":20,"y":127,"z":-14},{"bone":14,"x":0,"y":124,"z":0},{"bone":15,"x":7,"y":0,"z":0}]},
    {"frameId":4,"transformCount":16,"transforms":[{"bone":0,"x":0,"y":0,"z":-21},{"bone":1,"x":-51,"y":0,"z":0},{"bone":3,"x":15,"y":0,"z":0},{"bone":4,"x":0,"y":0,"z":30},{"bone":5,"x":51,"y":0,"z":0},{"bone":7,"x":17,"y":0,"z":0},{"bone":9,"x":0,"y":-43,"z":23},{"bone":10,"x":0,"y":88,"z":0},{"bone":11,"x":15,"y":0,"z":0},{"bone":13,"x":20,"y":127,"z":-14},{"bone":14,"x":0,"y":145,"z":0},{"bone":15,"x":15,"y":0,"z":0}]},
    {"frameId":5,"transformCount":16,"transforms":[{"bone":0,"x":0,"y":0,"z":-21},{"bone":1,"x":-51,"y":0,"z":0},{"bone":3,"x":30,"y":0,"z":0},{"bone":4,"x":0,"y":0,"z":30},{"bone":5,"x":51,"y":0,"z":0},{"bone":7,"x":34,"y":0,"z":0},{"bone":9,"x":0,"y":-43,"z":23},{"bone":10,"x":0,"y":103,"z":0},{"bone":11,"x":31,"y":0,"z":0},{"bone":13,"x":20,"y":127,"z":-14},{"bone":14,"x":0,"y":188,"z":0},{"bone":15,"x":30,"y":0,"z":0}]}
  ]
}
